whylogs_container_client/__init__.py
whylogs_container_client/api/__init__.py
whylogs_container_client/api/debug/__init__.py
whylogs_container_client/api/debug/debug_embeddings.py
whylogs_container_client/api/debug/debug_evaluate.py
whylogs_container_client/api/debug/debug_policies.py
whylogs_container_client/api/llm/__init__.py
whylogs_container_client/api/llm/evaluate.py
whylogs_container_client/api/llm/evaluate_sqs.py
whylogs_container_client/api/llm/lightllm_evaluate_v0_integrations_lightllm_evaluate_post.py
whylogs_container_client/api/llm/list_metrics.py
whylogs_container_client/api/llm/log_llm.py
whylogs_container_client/api/llm/policy.py
whylogs_container_client/api/manage/__init__.py
whylogs_container_client/api/manage/debug_info.py
whylogs_container_client/api/manage/health.py
whylogs_container_client/api/manage/health_llm_deep.py
whylogs_container_client/api/manage/healthz.py
whylogs_container_client/api/manage/publish.py
whylogs_container_client/api/manage/status.py
whylogs_container_client/api/profile/__init__.py
whylogs_container_client/api/profile/log.py
whylogs_container_client/api/profile/log_embeddings.py
whylogs_container_client/api/profile/log_pubsub.py
whylogs_container_client/api/profile/log_pubsub_embedding.py
whylogs_container_client/api/ui/__init__.py
whylogs_container_client/api/ui/ui_policy.py
whylogs_container_client/client.py
whylogs_container_client/errors.py
whylogs_container_client/models/__init__.py
whylogs_container_client/models/action.py
whylogs_container_client/models/action_type.py
whylogs_container_client/models/available_metrics.py
whylogs_container_client/models/debug_llm_validate_request.py
whylogs_container_client/models/debug_llm_validate_request_additional_data.py
whylogs_container_client/models/debug_llm_validate_request_metadata_type_0.py
whylogs_container_client/models/debug_policies_response_debug_policies.py
whylogs_container_client/models/embedding_request.py
whylogs_container_client/models/evaluation_result.py
whylogs_container_client-2.3.0.dist-info/METADATA
whylogs_container_client-2.3.0.dist-info/WHEEL
whylogs_container_client-2.3.0.dist-info/RECORD
